{"data":{"site":{"siteMetadata":{"title":"Un test sous Gatsby"}},"allMarkdownRemark":{"edges":[{"node":{"excerpt":"Ce soir, la lune rêve avec plus de paresse; Ainsi qu’une beauté, sur de nombreux coussins, Qui d’une main distraite et légère caresse Avant…","fields":{"slug":"/bye-felicia/"},"frontmatter":{"date":"February 19, 2019","title":"Tristesses de la lune"}}},{"node":{"excerpt":"Ta tête, ton geste, ton air Sont beaux comme un beau paysage; Le rire joue en ton visage Comme un vent frais dans un ciel clair.   Le…","fields":{"slug":"/hello-charles/"},"frontmatter":{"date":"February 17, 2019","title":"A celle qui est trop gaie"}}}]}},"pageContext":{}}